grammaticommit/__init__.py
grammaticommit/commit-msg
grammaticommit/grammaticommit.py
grammaticommit-0.5.data/scripts/grammaticommit
grammaticommit-0.5.dist-info/LICENSE
grammaticommit-0.5.dist-info/METADATA
grammaticommit-0.5.dist-info/WHEEL
grammaticommit-0.5.dist-info/top_level.txt
grammaticommit-0.5.dist-info/RECORD
