Metadata-Version: 2.1
Name: grammaticommit
Version: 0.5
Summary: Fix your damn commit message grammar!
Home-page: https://github.com/FdelMazo/grammaticommit
Author: FdelMazo
License: UNKNOWN
Platform: UNKNOWN
Classifier: Programming Language :: Python :: 3
Requires-Python: >3
Requires-Dist: termcolor (>=1.1.0)
Requires-Dist: Pattern (>=3.6)
